sqlite_utils_sqlite_url/__init__.py
sqlite_utils_sqlite_url/version.py
sqlite_utils_sqlite_url-0.1.0.dist-info/METADATA
sqlite_utils_sqlite_url-0.1.0.dist-info/WHEEL
sqlite_utils_sqlite_url-0.1.0.dist-info/entry_points.txt
sqlite_utils_sqlite_url-0.1.0.dist-info/top_level.txt
sqlite_utils_sqlite_url-0.1.0.dist-info/RECORD
