Metadata-Version: 2.1
Name: sqlite-utils-sqlite-url
Version: 0.1.0
Summary: TODO
Author: Alex Garcia
License: Apache-2.0
Project-URL: Homepage, https://github.com/asg017/sqlite-url
Project-URL: Changelog, https://github.com/asg017/sqlite-url/releases
Project-URL: Issues, https://github.com/asg017/sqlite-url/issues
Requires-Dist: sqlite-utils
Requires-Dist: sqlite-url
